MANIFEST.in
README.md
pyproject.toml
setup.py
src/omuse/__init__.py
src/omuse/version.py
src/omuse/community/__init__.py
src/omuse/ext/__init__.py
src/omuse/ext/dispersion_relations.py
src/omuse/ext/grid_generators.py
src/omuse/ext/grid_remappers.py
src/omuse/ext/hurricane_models.py
src/omuse/ext/seawater.py
src/omuse/ext/simple_triangulations.py
src/omuse/ext/spherical_geometry.py
src/omuse/ext/_seawater/README
src/omuse/ext/_seawater/__init__.py
src/omuse/ext/_seawater/density.py
src/omuse/ext/_seawater/heat.py
src/omuse/ext/_seawater/misc.py
src/omuse/ext/_seawater/salinity.py
src/omuse/ext/_seawater/test.py
src/omuse/ext/eddy_tracker/SSH_t.t0.1_42l_nccs01.avg0315-0325.nc
src/omuse/ext/eddy_tracker/__init__.py
src/omuse/ext/eddy_tracker/haversine_distmat_python.py
src/omuse/ext/eddy_tracker/interface.py
src/omuse/ext/eddy_tracker/make_eddy_track_AVISO.py
src/omuse/ext/eddy_tracker/make_eddy_track_ROMS.py
src/omuse/ext/eddy_tracker/make_eddy_tracker_list_obj.py
src/omuse/ext/eddy_tracker/py_eddy_tracker_classes.py
src/omuse/ext/eddy_tracker/py_eddy_tracker_property_classes.py
src/omuse/ext/eddy_tracker/roms_grid.py
src/omuse/ext/eddy_tracker/rossrad.dat
src/omuse/ext/eddy_tracker/track_eddy.py
src/omuse/io/__init__.py
src/omuse/io/adcirc.py
src/omuse/io/pop_netcdf.py
src/omuse/units/__init__.py
src/omuse/units/constants.py
src/omuse/units/quantities.py
src/omuse/units/units.py
src/omuse_framework.egg-info/PKG-INFO
src/omuse_framework.egg-info/SOURCES.txt
src/omuse_framework.egg-info/dependency_links.txt
src/omuse_framework.egg-info/requires.txt
src/omuse_framework.egg-info/top_level.txt
support/__init__.py
support/classifiers.py
support/setup_codes.py